{
  "DataEntityMetadataJson": {
    "[dbo].[A_GABE_V_DIRETORIA]": "{\"name\":\"[dbo].[A_GABE_V_DIRETORIA]\",\"title\":\"[dbo].[A_GABE_V_DIRETORIA]\",\"x-ms-permission\":\"read-only\",\"x-ms-capabilities\":{\"sortRestrictions\":{\"sortable\":true},\"filterRestrictions\":{\"filterable\":true},\"selectRestrictions\":{\"selectable\":true},\"filterFunctionSupport\":[\"lt\",\"le\",\"eq\",\"ne\",\"gt\",\"ge\",\"min\",\"max\",\"countdistinct\",\"add\",\"sub\",\"mul\",\"div\",\"mod\",\"negate\",\"now\",\"not\",\"and\",\"or\",\"day\",\"month\",\"year\",\"hour\",\"minute\",\"second\",\"date\",\"time\",\"totaloffsetminutes\",\"totalseconds\",\"round\",\"floor\",\"ceiling\",\"contains\",\"startswith\",\"endswith\",\"length\",\"indexof\",\"replace\",\"substring\",\"substringof\",\"tolower\",\"toupper\",\"trim\",\"concat\",\"sum\",\"min\",\"max\",\"average\",\"countdistinct\",\"null\"]},\"schema\":{\"type\":\"array\",\"items\":{\"type\":\"object\",\"required\":[\"ID_DIRETORIA\",\"NOM_DIRETORIA\",\"QTD_BOLSA_ANO\",\"IND_DISPONIVEL\"],\"properties\":{\"ID_DIRETORIA\":{\"title\":\"ID_DIRETORIA\",\"x-ms-capabilities\":{\"filterFunctions\":[\"lt\",\"le\",\"eq\",\"ne\",\"gt\",\"ge\",\"min\",\"max\",\"countdistinct\",\"add\",\"sub\",\"mul\",\"div\",\"mod\",\"negate\",\"sum\",\"average\"]},\"type\":\"integer\",\"format\":\"int32\",\"minimum\":-2147483648,\"maximum\":2147483647,\"x-ms-permission\":\"read-write\",\"x-ms-sort\":\"none\"},\"NOM_DIRETORIA\":{\"title\":\"NOM_DIRETORIA\",\"x-ms-capabilities\":{\"filterFunctions\":[\"lt\",\"le\",\"eq\",\"ne\",\"gt\",\"ge\",\"min\",\"max\",\"countdistinct\",\"contains\",\"startswith\",\"endswith\",\"length\",\"indexof\",\"replace\",\"substring\",\"substringof\",\"tolower\",\"toupper\",\"trim\",\"concat\"]},\"type\":\"string\",\"maxLength\":100,\"x-ms-permission\":\"read-write\",\"x-ms-sort\":\"none\"},\"QTD_BOLSA_ANO\":{\"title\":\"QTD_BOLSA_ANO\",\"x-ms-capabilities\":{\"filterFunctions\":[\"lt\",\"le\",\"eq\",\"ne\",\"gt\",\"ge\",\"min\",\"max\",\"countdistinct\",\"add\",\"sub\",\"mul\",\"div\",\"mod\",\"negate\",\"sum\",\"average\"]},\"type\":\"integer\",\"format\":\"int32\",\"minimum\":-2147483648,\"maximum\":2147483647,\"x-ms-permission\":\"read-write\",\"x-ms-sort\":\"none\"},\"ANO\":{\"title\":\"ANO\",\"x-ms-capabilities\":{\"filterFunctions\":[\"lt\",\"le\",\"eq\",\"ne\",\"gt\",\"ge\",\"min\",\"max\",\"countdistinct\",\"add\",\"sub\",\"mul\",\"div\",\"mod\",\"negate\",\"sum\",\"average\"]},\"type\":\"integer\",\"format\":\"int32\",\"minimum\":-2147483648,\"maximum\":2147483647,\"x-ms-permission\":\"read-write\",\"x-ms-sort\":\"none\"},\"QTD_CONSUMIDA\":{\"title\":\"QTD_CONSUMIDA\",\"x-ms-capabilities\":{\"filterFunctions\":[\"lt\",\"le\",\"eq\",\"ne\",\"gt\",\"ge\",\"min\",\"max\",\"countdistinct\",\"add\",\"sub\",\"mul\",\"div\",\"mod\",\"negate\",\"sum\",\"average\"]},\"type\":\"integer\",\"format\":\"int32\",\"minimum\":-2147483648,\"maximum\":2147483647,\"x-ms-permission\":\"read-write\",\"x-ms-sort\":\"none\"},\"QTD_DISPONIVEL\":{\"title\":\"QTD_DISPONIVEL\",\"x-ms-capabilities\":{\"filterFunctions\":[\"lt\",\"le\",\"eq\",\"ne\",\"gt\",\"ge\",\"min\",\"max\",\"countdistinct\",\"add\",\"sub\",\"mul\",\"div\",\"mod\",\"negate\",\"sum\",\"average\"]},\"type\":\"integer\",\"format\":\"int32\",\"minimum\":-2147483648,\"maximum\":2147483647,\"x-ms-permission\":\"read-write\",\"x-ms-sort\":\"none\"},\"IND_DISPONIVEL\":{\"title\":\"IND_DISPONIVEL\",\"x-ms-capabilities\":{\"filterFunctions\":[\"lt\",\"le\",\"eq\",\"ne\",\"gt\",\"ge\",\"min\",\"max\",\"countdistinct\",\"add\",\"sub\",\"mul\",\"div\",\"mod\",\"negate\",\"sum\",\"average\"]},\"type\":\"integer\",\"format\":\"int32\",\"minimum\":-2147483648,\"maximum\":2147483647,\"x-ms-permission\":\"read-write\",\"x-ms-sort\":\"none\"}}},\"x-ms-permission\":\"read-only\"}}"
  },
  "EntityName": "A_GABE_V_DIRETORIA",
  "TableName": "[dbo].[A_GABE_V_DIRETORIA]"
}